autobot/__init__.py
autobot/autobot.py
autobot/constants.py
autobot/main.py
autobot/configuration/__init__.py
autobot/configuration/config.py
autobot/configuration/settings.py
autobot/factory/__init__.py
autobot/factory/callbackhandlerfactory.py
autobot/filters/__init__.py
autobot/filters/idfilter.py
autobot/filters/textequals.py
autobot/handler/__init__.py
autobot/handler/ptb/__init__.py
autobot/handler/ptb/filterregexhandler.py
autobot/handler/response/__init__.py
autobot/handler/response/replymarkupbuilder.py
autobot/handler/response/responsehandler.py
autobot/plugins/__init__.py
autobot/plugins/pluginsloader.py
autobot/plugins/response/__init__.py
autobot/plugins/response/responsehandlercommand.py
autobot/plugins/response/responsehandlerphoto.py
autobot/plugins/response/responsehandlertext.py
autobot/version/__init__.py
autobot/version/version.py
telegram_autobot-0.0.20.dist-info/LICENSE
telegram_autobot-0.0.20.dist-info/METADATA
telegram_autobot-0.0.20.dist-info/WHEEL
telegram_autobot-0.0.20.dist-info/entry_points.txt
telegram_autobot-0.0.20.dist-info/top_level.txt
telegram_autobot-0.0.20.dist-info/RECORD
