Metadata-Version: 2.1
Name: telegram-autobot
Version: 0.0.20
Summary: Build an interactive Telegram bot with some JSON files
Home-page: https://github.com/andreacioni/autobot
Author: Andrea Cioni
Author-email: cioni95@rocketmail.com
Classifier: Programming Language :: Python :: 3
Classifier: License :: OSI Approved :: MIT License
Classifier: Operating System :: OS Independent
License-File: LICENSE
